{
   "Anthropology (Concentration in Archaeology)": "AN27",
   "Anthropology (Concentration in Biological Anthropology)": "AN26",
   "Anthropology (Concentration in Sociocultural Anthropology)": "AN28",
   "Anthropology with a Concentration in Climate Change and Human Solutions": "AN30",
   "Biological Anthropology": "AN29",
   "Bioengineering": "BE25",
   "Bioengineering (Bioinformatics)": "BE28",
   "Bioengineering: BioSystems": "BE29",
   "Bioengineering (Biotechnology)": "BE27",
   "Available to students admitted to UCSD in Fall 2018 or later": "",
   "Biology with Specialization in Bioinformatics": "BI34",
   "Ecology, Behavior, and Evolution": "BI30",
   "General Biology": "BI31",
   "Human Biology": "BI35",
   "Microbiology": "BI32",
   "Molecular and Cell Biology": "BI37",
   "Neurobiology": "BI38",
   "Available to students admitted to UCSD in Fall 2017 or earlier": "",
   "Biochemistry and Cell Biology (see also Chemistry and Biochemistry CH31)": "BI29",
   "Molecular Biology": "BI33",
   "Physiology and Neuroscience": "BI36",
   "Black Diaspora and African American Studies": "AA25",
   "Chemical Engineering": "CE25",
   "Biochemistry": "CH38",
   "Chemistry": "CH25",
   "Environmental Chemistry": "CH34",
   "Molecular Synthesis": "CH36",
   "Pharmacological Chemistry": "CH35",
   "Chinese Studies": "CN25",
   "Classical Studies": "CL25",
   "Cognitive Science": "CG25",
   "Cognitive and Behavioral Neuroscience": "PC34",
   "Cognitive Science with a Specialization in Clinical Aspects of Cognition": "CG31",
   "Cognitive Science with a Specialization in Design and Interaction": "CG33",
   "Cognitive Science with a Specialization in Language and Culture": "CG34",
   "Cognitive Science with a Specialization in Machine Learning and Neural Computation": "CG35",
   "Cognitive Science with a Specialization in Neuroscience": "CG29",
   "Communication": "CM26",
   "Computer Engineering (See also Electrical and Computer Engineering EC26)": "CS25",
   "Computer Science (B.S.)": "CS26",
   "Computer Science with a Specialization in Bioinformatics": "CS27",
   "Critical Gender Studies": "CR25",
   "Data Science": "DS25",
   "Business Economics": "EN30",
   "Economics": "EN25",
   "Economics-Public Policy (B.A./MPP only)": "EN29",
   "Joint Major in Mathematics and Economics": "EN28",
   "Education Sciences": "ED25",
   "Computer Engineering (see also Computer Science and Engineering CS25)": "EC26",
   "Electrical Engineering": "EC27",
   "Engineering Physics": "EC28",
   "Electrical Engineering & Society (B.A.)": "EC37",
   "Environmental Systems (Earth Sciences)": "ES25",
   "Environmental Systems (Ecology, Behavior, and Evolution)": "ES26",
   "Environmental Systems (Environmental Chemistry)": "ES27",
   "Environmental Systems (Environmental Policy)": "ES28",
   "Ethnic Studies": "ET25",
   "German Studies": "GS25",
   "Global Health (B.A.)": "GH25",
   "Global Health (B.S.)": "GH26",
   "Global South Studies": "GL25",
   "Public Health": "PB25",
   "Public Health with Concentration in Biostatistics": "PB26",
   "Public Health with Concentration in Climate and Environmental Sciences": "PB27",
   "Public Health with Concentration in Community Health Sciences": "PB28",
   "Public Health with Concentration in Epidemiology": "PB29",
   "Public Health with Concentration in Health Policy and Management Sciences": "PB30",
   "Public Health with Concentration in Medicine Sciences": "PB31",
   "History": "HI25",
   "Human Developmental Sciences (B.A.)": "HS25",
   "Human Developmental Sciences (B.S.)": "HS26",
   "Human Developmental Sciences with a Specialization in Equity and Diversity": "HS27",
   "Human Developmental Sciences with a Specialization in Healthy Aging": "HS28",
   "Eleanor Roosevelt College Individual Studies": "IN27",
   "Muir College Special Project Major": "IN25",
   "Revelle College Individual Major": "IN26",
   "Thurgood Marshall College Individual Studies": "IN29",
   "Warren College Individual Studies": "IN28",
   "Sixth College Individual Studies": "IN30",
   "Seventh College Individual Studies": "IN32",
   "International Studies \u2014 Anthropology": "IS25",
   "International Studies \u2014 Economics": "IS26",
   "International Studies \u2014 History": "IS27",
   "International Studies \u2014 Linguistics": "IS28",
   "International Studies \u2014 Literature": "IS29",
   "International Studies \u2014 Political Science": "IS30",
   "International Studies \u2014 Sociology": "IS31",
   "International Studies \u2014 Economics (Jt BA/MIA)": "IS32",
   "International Studies \u2014 Political Science (Jt BA/MIA)": "IS33",
   "International Studies\u00a0\u2014 International Business": "IS34",
   "International Studies\u00a0\u2014 International Business (Jt BA/MIA)": "IS35",
   "International Studies \u2014 Philosophy": "IS36",
   "Italian Studies": "IT25",
   "Japanese Studies": "JA25",
   "Jewish Studies": "JS25",
   "Latin American Studies": "LA25",
   "Latin American Studies with a Concentration in Mexico": "LA26",
   "Latin American Studies with a Concentration in Migration and Border Studies": "LA27",
   "Language Studies": "LN33",
   "Linguistics": "LN25",
   "Linguistics (Specialization in Cognition and Language)": "LN32",
   "Linguistics (Specialization in Language and Society)": "LN29",
   "Linguistics (Specialization in Speech and Language Sciences)": "LN34",
   "Literature/ Writing": "LT34",
   "Literatures in English": "LT36",
   "Spanish Literature": "LT33",
   "World Literature and Culture": "LT41",
   "Joint Major Mathematics & Economics": "MA33",
   "Mathematics": "MA29",
   "Mathematics (Applied)": "MA27",
   "Mathematics \u2014 Applied Science": "MA31",
   "Mathematics \u2014 Computer Science": "MA30",
   "Mathematics \u2014 Secondary Education": "MA32",
   "Probability & Statistics": "MA35",
   "Aerospace Engineering": "MC25",
   "Mechanical Engineering": "MC27",
   "Mechanical Engineering with a Specialization in Controls and Robotics": "MC34",
   "Mechanical Engineering with a Specialization in Fluid Mechanics and Thermal Systems": "MC33",
   "Mechanical Engineering with a Specialization in Materials Science and Engineering": "MC32",
   "Mechanical Engineering with a Specialization in Mechanics of Materials": "MC31",
   "Mechanical Engineering with a Specialization in Renewable Energy and Environmental Flows": "MC30",
   "Interdisciplinary Computing and the Arts": "VA29",
   "Music": "MU25",
   "Music Humanities": "MU26",
   "Nanoengineering": "NA25",
   "Philosophy": "PL25",
   "General Physics": "PY30",
   "General Physics/ Secondary Education": "PY31",
   "Physics": "PY29",
   "Physics-Biophysics": "PY26",
   "Physics with a Specialization in Astrophysics": "PY34",
   "Physics with a Specialization in Computational Physics": "PY33",
   "Physics with a Specialization in Earth Sciences": "PY28",
   "Physics with a Specialization in Materials Physics": "PY32",
   "Political Science": "PS25",
   "Political Science/American Politics": "PS26",
   "Political Science/Comparative Politics": "PS27",
   "Political Sciences/International Relations": "PS28",
   "Political Science/Political Theory": "PS29",
   "Political Science/Public Law": "PS30",
   "Political Science/Public Policy": "PS31",
   "Political Science/Data Analytics": "PS32",
   "Political Science/International Affairs (B.A./MIA only)": "PS33",
   "Political Science/Race, Ethnicity, and Politics": "PS34",
   "Psychology (B.A.)": "PC25",
   "Psychology (B.S.)": "PC26",
   "Psychology with a Specialization in Clinical Psychology": "PC28",
   "Psychology with a Specialization in Cognitive Psychology": "PC29",
   "Psychology with a Specialization in Developmental Psychology": "PC30",
   "Psychology with a Specialization in Human Health": "PC31",
   "Psychology with a Specialization in Sensation and Perception": "PC32",
   "Psychology with a Specialization in Social Psychology": "PC33",
   "Business Psychology": "PC35",
   "Study of Religion": "RE26",
   "Russian, East European and Eurasian Studies": "RU26",
   "Marine Biology": "SI29",
   "Oceanic and Atmospheric Sciences": "SI30",
   "Geosciences": "SI31",
   "Sociology": "SO25",
   "Sociology-American Studies": "SO27",
   "Sociology-Culture and Communication": "SO28",
   "Sociology-Economy and Society": "SO29",
   "Sociology-International Studies": "SO30",
   "Sociology-Law and Society": "SO31",
   "Sociology-Science and Medicine": "SO32",
   "Sociology-Social Inequality": "SO33",
   "Structural Engineering": "SE27",
   "Dance": "TH27",
   "Theatre": "TH26",
   "Undeclared": "UN27",
   "Undeclared \u2014 Humanities/ Arts": "UNHA",
   "Undeclared \u2014 Physical Sciences": "UNPS",
   "Undeclared \u2014 Social Sciences": "UNSS",
   "Urban Studies and Planning": "US26",
   "Real Estate and Development": "US27",
   "Visual Arts (Art History/ Criticism)": "VA26",
   "Visual Arts (Media)": "VA27",
   "Visual Arts (Studio)": "VA28",
   "Speculative Design": "VA30"
}